mp2hudcolor.cpython-38-x86_64-linux-gnu.so
mp2hudcolor/mp2hudcolor.c
mp2hudcolor-1.0.13.dist-info/RECORD
mp2hudcolor-1.0.13.dist-info/zip-safe
mp2hudcolor-1.0.13.dist-info/METADATA
mp2hudcolor-1.0.13.dist-info/WHEEL
mp2hudcolor-1.0.13.dist-info/top_level.txt
mp2hudcolor-1.0.13.dist-info/LICENSE
