Metadata-Version: 2.1
Name: mp2hudcolor
Version: 1.0.13
Summary: Modifies an existing NTWK file for Metroid Prime 2: Echoes and changing the color of the HUD
Home-page: https://github.com/toasterparty/mp2hudcolor
Author: toasterparty
Author-email: toasterparty@derpymail.org
License: License :: OSI Approved :: MIT License
Classifier: License :: OSI Approved :: MIT License
Classifier: Development Status :: 4 - Beta
Classifier: Intended Audience :: Developers
Classifier: Programming Language :: Python :: 3 :: Only
Classifier: Programming Language :: Python :: 3.8
Classifier: Programming Language :: Python :: 3.9
Classifier: Programming Language :: Python :: 3.10
Classifier: Programming Language :: Python :: 3.11
Classifier: Programming Language :: Python :: 3.12
Requires-Python: >=3.8
License-File: LICENSE
